superfunctions_fastapi/__init__.py
superfunctions_fastapi/adapter.py
superfunctions_fastapi-0.1.0.dist-info/METADATA
superfunctions_fastapi-0.1.0.dist-info/WHEEL
superfunctions_fastapi-0.1.0.dist-info/RECORD
